geofeed_validator/__init__.py
geofeed_validator/result.py
geofeed_validator/utils.py
geofeed_validator/fields/__init__.py
geofeed_validator/fields/base.py
geofeed_validator/fields/draft02_extension.py
geofeed_validator/validator/__init__.py
geofeed_validator/validator/base.py
geofeed_validator/validator/draft02.py
geofeed_validator-0.6.1.data/scripts/geofeed-validator.py
geofeed_validator-0.6.1.dist-info/COPYING
geofeed_validator-0.6.1.dist-info/METADATA
geofeed_validator-0.6.1.dist-info/WHEEL
geofeed_validator-0.6.1.dist-info/top_level.txt
geofeed_validator-0.6.1.dist-info/RECORD
