Metadata-Version: 2.1
Name: geofeed-validator
Version: 0.6.1
Summary: Validator library for self-published geo feeds
Home-page: https://github.com/anexia-it/geofeed-validator
Author: Stephan Peijnik
Author-email: speijnik@anexia-it.com
License: AGPLv3+
Platform: UNKNOWN
Classifier: Development Status :: 5 - Production/Stable
Classifier: Environment :: Console
Classifier: Intended Audience :: Developers
Classifier: Intended Audience :: System Administrators
Classifier: License :: OSI Approved :: GNU Affero General Public License v3 or later (AGPLv3+)
Classifier: Operating System :: OS Independent
Classifier: Programming Language :: Python
Classifier: Programming Language :: Python :: 3
Classifier: Programming Language :: Python :: 3.5
Classifier: Programming Language :: Python :: 3.6
Classifier: Programming Language :: Python :: 3.7
Classifier: Programming Language :: Python :: 3.8
Classifier: Topic :: Software Development :: Libraries :: Python Modules
Requires-Dist: pycountry (>=20.7.3)
Requires-Dist: netaddr (>=0.7.11)
